evassistant/__init__.py
evassistant/evassistant.py
evassistant-0.0.7.dist-info/LICENSE
evassistant-0.0.7.dist-info/METADATA
evassistant-0.0.7.dist-info/WHEEL
evassistant-0.0.7.dist-info/top_level.txt
evassistant-0.0.7.dist-info/RECORD
