Metadata-Version: 2.1
Name: evassistant
Version: 0.0.7
Summary: tools for external validation of predication model
Home-page: https://github.com/liuyp2080/evassistant
Author: jeff liu
Author-email: liuyp2080@163.com
License: UNKNOWN
Project-URL: Bug Tracker, https://github.com/pypa/sampleproject/issues
Platform: UNKNOWN
Classifier: Programming Language :: Python :: 3
Classifier: License :: OSI Approved :: MIT License
Classifier: Operating System :: OS Independent
Requires-Python: >=3.6
